devtools_regex_cheat/__init__.py
devtools_regex_cheat-1.0.1.dist-info/METADATA
devtools_regex_cheat-1.0.1.dist-info/WHEEL
devtools_regex_cheat-1.0.1.dist-info/top_level.txt
devtools_regex_cheat-1.0.1.dist-info/RECORD
